kord/__init__.py
kord/errors.py
kord/instruments.py
kord/keys/__init__.py
kord/keys/chords.py
kord/keys/scales.py
kord/keys/test_chords.py
kord/keys/test_scales.py
kord/notes/__init__.py
kord/notes/intervals.py
kord/notes/pitch.py
kord/notes/test_notes.py
kord/notes/constants/__init__.py
kord/notes/constants/double_flats.py
kord/notes/constants/double_sharps.py
kord/notes/constants/flats.py
kord/notes/constants/naturals.py
kord/notes/constants/sharps.py
kord/parsers/__init__.py
kord/parsers/chord_parser.py
kord/parsers/pitch_parser.py
kord/parsers/test_chord_parser.py
kord/parsers/test_pitch_parser.py
kord-5.4.data/data/fretboard/fretboard.py
kord-5.4.data/data/fretboard/tuner.py
kord-5.4.data/data/fretboard/tunings/banjo.json
kord-5.4.data/data/fretboard/tunings/bass.json
kord-5.4.data/data/fretboard/tunings/guitar.json
kord-5.4.data/data/fretboard/tunings/ronroco.json
kord-5.4.data/data/fretboard/tunings/ukulele.json
kord-5.4.dist-info/LICENSE
kord-5.4.dist-info/METADATA
kord-5.4.dist-info/WHEEL
kord-5.4.dist-info/top_level.txt
kord-5.4.dist-info/RECORD
