Metadata-Version: 2.1
Name: kord
Version: 5.4
Summary: programming framework for developing music applications
Home-page: https://github.com/synestematic/kord
Author: Federico Rizzo
Author-email: synestem@ticATgmail.com
License: MIT
Classifier: Programming Language :: Python :: 3 :: Only
Classifier: Development Status :: 5 - Production/Stable
Classifier: License :: OSI Approved :: MIT License
Classifier: Operating System :: POSIX :: Linux
Classifier: Operating System :: MacOS :: MacOS X
License-File: LICENSE
Requires-Dist: bestia>=5.0
